clean_talk_client/__init__.py
clean_talk_client/auth_result.py
clean_talk_client/clean_talk_prediction_client.py
clean_talk_client/kolas_ai_oauth_client.py
clean_talk_client/message.py
clean_talk_client/predict_request.py
clean_talk_client/predict_response.py
clean_talk_client/prediction_result.py
clean_talk_client/request_exception_handler.py
clean_talk_client/exception/account_balance_empty_exception.py
clean_talk_client/exception/clean_talk_exception.py
clean_talk_client/exception/project_dataset_not_configured_exception.py
clean_talk_client/exception/project_not_active_exception.py
clean_talk_client/exception/project_not_found_exception.py
clean_talk_client-1.0.4.dist-info/licenses/LICENSE
clean_talk_client-1.0.4.dist-info/METADATA
clean_talk_client-1.0.4.dist-info/WHEEL
clean_talk_client-1.0.4.dist-info/top_level.txt
clean_talk_client-1.0.4.dist-info/RECORD
