Metadata-Version: 2.4
Name: clean_talk_client
Version: 1.0.4
Summary: Official Clean Talk client for Python applications.
Author-email: "kolas.ai" <info@kolas.ai>
License:                                  Apache License
Requires-Python: >=3.9
License-File: LICENSE
Requires-Dist: requests>=2.32
Dynamic: license-file
